lpdb_python/__init__.py
lpdb_python/defs.py
lpdb_python/session.py
lpdb_python/async_session/__init__.py
lpdb_python/async_session/async_session.py
lpdb_python-0.1.1.dist-info/licenses/LICENSE
lpdb_python-0.1.1.dist-info/METADATA
lpdb_python-0.1.1.dist-info/WHEEL
lpdb_python-0.1.1.dist-info/top_level.txt
lpdb_python-0.1.1.dist-info/RECORD
