Metadata-Version: 2.4
Name: lpdb_python
Version: 0.1.1
Author-email: ElectricalBoy <electricalboy01@gmail.com>
License-Expression: MIT
Project-URL: Homepage, https://github.com/ElectricalBoy/LPDB_python
Project-URL: Changelog, https://github.com/ElectricalBoy/LPDB_python/releases
Project-URL: Issues, https://github.com/ElectricalBoy/LPDB_python/issues
Classifier: Programming Language :: Python :: 3
Classifier: Operating System :: OS Independent
Requires-Python: >=3.12
License-File: LICENSE
Requires-Dist: requests>=2.32.5
Provides-Extra: async
Requires-Dist: aiohttp>=3.13.2; extra == "async"
Dynamic: license-file
